ai21/__init__.py
ai21/ai21_env_config.py
ai21/clients/__init__.py
ai21/clients/aws/__init__.py
ai21/clients/aws/aws_authorization.py
ai21/clients/azure/__init__.py
ai21/clients/azure/ai21_azure_client.py
ai21/clients/bedrock/__init__.py
ai21/clients/bedrock/_stream_decoder.py
ai21/clients/bedrock/ai21_bedrock_client.py
ai21/clients/bedrock/bedrock_model_id.py
ai21/clients/common/__init__.py
ai21/clients/common/agents/__init__.py
ai21/clients/common/agents/agents.py
ai21/clients/common/agents/run.py
ai21/clients/common/auth/__init__.py
ai21/clients/common/auth/gcp_authorization.py
ai21/clients/common/chat_base.py
ai21/clients/common/conversational_rag.py
ai21/clients/common/maestro/__init__.py
ai21/clients/common/maestro/maestro.py
ai21/clients/common/maestro/run.py
ai21/clients/launchpad/__init__.py
ai21/clients/launchpad/ai21_launchpad_client.py
ai21/clients/studio/__init__.py
ai21/clients/studio/ai21_client.py
ai21/clients/studio/async_ai21_client.py
ai21/clients/studio/resources/__init__.py
ai21/clients/studio/resources/agents/__init__.py
ai21/clients/studio/resources/agents/agents.py
ai21/clients/studio/resources/agents/async_agents.py
ai21/clients/studio/resources/batch/__init__.py
ai21/clients/studio/resources/batch/async_batches.py
ai21/clients/studio/resources/batch/base_batches.py
ai21/clients/studio/resources/batch/batches.py
ai21/clients/studio/resources/beta/__init__.py
ai21/clients/studio/resources/beta/async_beta.py
ai21/clients/studio/resources/beta/beta.py
ai21/clients/studio/resources/chat/__init__.py
ai21/clients/studio/resources/chat/async_chat_completions.py
ai21/clients/studio/resources/chat/base_chat_completions.py
ai21/clients/studio/resources/chat/chat_completions.py
ai21/clients/studio/resources/constants.py
ai21/clients/studio/resources/maestro/__init__.py
ai21/clients/studio/resources/maestro/maestro.py
ai21/clients/studio/resources/maestro/run.py
ai21/clients/studio/resources/studio_chat.py
ai21-4.2.0.dist-info/LICENSE
ai21-4.2.0.dist-info/METADATA
ai21-4.2.0.dist-info/WHEEL
ai21-4.2.0.dist-info/RECORD
