Metadata-Version: 2.1
Name: ai21
Version: 4.2.0
Summary: 
Author: AI21 Labs
Requires-Python: >=3.8,<4.0
Classifier: Programming Language :: Python :: 3
Classifier: Programming Language :: Python :: 3.8
Classifier: Programming Language :: Python :: 3.9
Classifier: Programming Language :: Python :: 3.10
Classifier: Programming Language :: Python :: 3.11
Classifier: Programming Language :: Python :: 3.12
Provides-Extra: aws
Provides-Extra: vertex
Requires-Dist: boto3 (>=1.28.82,<2.0.0) ; extra == "aws"
Requires-Dist: google-auth (>=2.31.0,<3.0.0) ; extra == "vertex"
Requires-Dist: httpx (>=0.27.0,<1.0.0)
Requires-Dist: pydantic (>=1.9.0,<3.0.0)
Requires-Dist: tenacity (>=8.3.0,<9.0.0)
Requires-Dist: typing-extensions (>=4.9.0,<5.0.0)
